dotp/__init__.py
dotp/cli.py
dotp/config.py
dotp/crypto.py
dotp/importexport.py
dotp/totp.py
dotp/tui.py
dotp/vault.py
dotp-0.1.4.dist-info/WHEEL
dotp-0.1.4.dist-info/entry_points.txt
dotp-0.1.4.dist-info/METADATA
dotp-0.1.4.dist-info/RECORD
