Metadata-Version: 2.3
Name: dotp
Version: 0.1.4
Summary: Dank One Time Password - CLI and TUI TOTP/Authenticator storage
Author: Bruno Rocha
Author-email: Bruno Rocha <rochacbruno@gmail.com>
License: AGPL-3.0-or-later
Requires-Dist: pyotp>=2.9.0
Requires-Dist: cyclopts>=3.0.0
Requires-Dist: rich>=13.0.0
Requires-Dist: textual>=1.0.0
Requires-Dist: cryptography>=42.0.0
Requires-Dist: pyperclip>=1.9.0
Requires-Dist: xdg-base-dirs>=6.0.0
Requires-Dist: pytest>=8.0.0 ; extra == 'dev'
Requires-Dist: pytest-cov>=4.1.0 ; extra == 'dev'
Requires-Python: >=3.11
Project-URL: Issues, https://github.com/rochacbruno/dotp/issues
Project-URL: Repository, https://github.com/rochacbruno/dotp
Provides-Extra: dev
